{
  "http://codingbat.com/java/Warmup-1": [
    "/prob/p187868",
    "/prob/p181646",
    "/prob/p154485",
    "/prob/p116624",
    "/prob/p140449",
    "/prob/p182873",
    "/prob/p184004",
    "/prob/p159227",
    "/prob/p191914",
    "/prob/p190570",
    "/prob/p123384",
    "/prob/p136351",
    "/prob/p161642",
    "/prob/p112564",
    "/prob/p183592",
    "/prob/p191022",
    "/prob/p192082",
    "/prob/p144535",
    "/prob/p178986",
    "/prob/p165701",
    "/prob/p100905",
    "/prob/p151713",
    "/prob/p199720",
    "/prob/p101887",
    "/prob/p172021",
    "/prob/p132134",
    "/prob/p177372",
    "/prob/p173784",
    "/prob/p125339",
    "/prob/p125268",
    "/prob/p196441"
  ],
  "http://codingbat.com/java/Warmup-2": [
    "/prob/p142270",
    "/prob/p101475",
    "/prob/p194667",
    "/prob/p186759",
    "/prob/p165666",
    "/prob/p117334",
    "/prob/p178318",
    "/prob/p184031",
    "/prob/p186031",
    "/prob/p136041",
    "/prob/p198640",
    "/prob/p171260",
    "/prob/p121596",
    "/prob/p126212",
    "/prob/p110019",
    "/prob/p170221",
    "/prob/p167430"
  ],
  "http://codingbat.com/java/String-1": [
    "/prob/p171896",
    "/prob/p161056",
    "/prob/p147483",
    "/prob/p184030",
    "/prob/p108853",
    "/prob/p163411",
    "/prob/p172267",
    "/prob/p130896",
    "/prob/p168564",
    "/prob/p143825",
    "/prob/p197720",
    "/prob/p130781",
    "/prob/p162477",
    "/prob/p174254",
    "/prob/p137729",
    "/prob/p103895",
    "/prob/p174148",
    "/prob/p144623",
    "/prob/p115863",
    "/prob/p139075",
    "/prob/p139076",
    "/prob/p138183",
    "/prob/p132118",
    "/prob/p194786",
    "/prob/p199216",
    "/prob/p196652",
    "/prob/p105745",
    "/prob/p172063",
    "/prob/p142247",
    "/prob/p110141",
    "/prob/p141494",
    "/prob/p151940",
    "/prob/p151359"
  ],
  "http://codingbat.com/java/Array-1": [
    "/prob/p185685",
    "/prob/p118976",
    "/prob/p167011",
    "/prob/p191991",
    "/prob/p175763",
    "/prob/p185139",
    "/prob/p112409",
    "/prob/p146256",
    "/prob/p190968",
    "/prob/p146449",
    "/prob/p101230",
    "/prob/p171022",
    "/prob/p175689",
    "/prob/p137188",
    "/prob/p145365",
    "/prob/p120347",
    "/prob/p109660",
    "/prob/p109537",
    "/prob/p199519",
    "/prob/p180840",
    "/prob/p118044",
    "/prob/p155713",
    "/prob/p185176",
    "/prob/p142455",
    "/prob/p197308",
    "/prob/p143461",
    "/prob/p128270"
  ],
  "http://codingbat.com/java/Logic-1": [
    "/prob/p159531",
    "/prob/p103360",
    "/prob/p141061",
    "/prob/p157733",
    "/prob/p183071",
    "/prob/p160543",
    "/prob/p137742",
    "/prob/p137365",
    "/prob/p100962",
    "/prob/p118290",
    "/prob/p159612",
    "/prob/p133158",
    "/prob/p193613",
    "/prob/p178728",
    "/prob/p110973",
    "/prob/p177181",
    "/prob/p137136",
    "/prob/p115243",
    "/prob/p113261",
    "/prob/p154188",
    "/prob/p140272",
    "/prob/p169213",
    "/prob/p179196",
    "/prob/p115233",
    "/prob/p115384",
    "/prob/p170833",
    "/prob/p120633",
    "/prob/p192267",
    "/prob/p153748",
    "/prob/p118077"
  ],
  "http://codingbat.com/java/Logic-2": [
    "/prob/p183562",
    "/prob/p148972",
    "/prob/p130788",
    "/prob/p182879",
    "/prob/p186753",
    "/prob/p138990",
    "/prob/p117019",
    "/prob/p198700",
    "/prob/p191363"
  ],
  "http://codingbat.com/java/String-2": [
    "/prob/p165312",
    "/prob/p147448",
    "/prob/p111624",
    "/prob/p123614",
    "/prob/p126880",
    "/prob/p136594",
    "/prob/p175762",
    "/prob/p134250",
    "/prob/p125185",
    "/prob/p152339",
    "/prob/p128796",
    "/prob/p109637",
    "/prob/p136417",
    "/prob/p159772",
    "/prob/p129952",
    "/prob/p194491",
    "/prob/p122943",
    "/prob/p180759",
    "/prob/p139564",
    "/prob/p170829",
    "/prob/p147538"
  ],
  "http://codingbat.com/java/String-3": [
    "/prob/p199171",
    "/prob/p192570",
    "/prob/p141736",
    "/prob/p198664",
    "/prob/p195714",
    "/prob/p197890",
    "/prob/p131516",
    "/prob/p139411",
    "/prob/p179479",
    "/prob/p121193",
    "/prob/p154137"
  ],
  "http://codingbat.com/java/Array-2": [
    "/prob/p162010",
    "/prob/p196640",
    "/prob/p136585",
    "/prob/p127384",
    "/prob/p111327",
    "/prob/p121853",
    "/prob/p194525",
    "/prob/p199612",
    "/prob/p104627",
    "/prob/p180920",
    "/prob/p186672",
    "/prob/p178353",
    "/prob/p136648",
    "/prob/p110222",
    "/prob/p191878",
    "/prob/p136254",
    "/prob/p168357",
    "/prob/p169260",
    "/prob/p159979",
    "/prob/p109783",
    "/prob/p102145",
    "/prob/p134300",
    "/prob/p137874",
    "/prob/p142539",
    "/prob/p105031",
    "/prob/p199484",
    "/prob/p100246",
    "/prob/p164144",
    "/prob/p169506",
    "/prob/p193753",
    "/prob/p196976",
    "/prob/p187050",
    "/prob/p105771",
    "/prob/p153059"
  ],
  "http://codingbat.com/java/Array-3": [
    "/prob/p189576",
    "/prob/p159339",
    "/prob/p125819",
    "/prob/p158767",
    "/prob/p134022",
    "/prob/p155405",
    "/prob/p104090",
    "/prob/p196409",
    "/prob/p193817"
  ],
  "http://codingbat.com/java/AP-1": [
    "/prob/p146974",
    "/prob/p179487",
    "/prob/p194530",
    "/prob/p123837",
    "/prob/p124620",
    "/prob/p183837",
    "/prob/p183407",
    "/prob/p191212",
    "/prob/p165941",
    "/prob/p134174",
    "/prob/p130124",
    "/prob/p139677",
    "/prob/p180365",
    "/prob/p121236",
    "/prob/p140485",
    "/prob/p148138",
    "/prob/p157900",
    "/prob/p197710",
    "/prob/p143482",
    "/prob/p139150",
    "/prob/p100369"
  ],
  "http://codingbat.com/java/Recursion-1": [
    "/prob/p154669",
    "/prob/p183649",
    "/prob/p120015",
    "/prob/p107330",
    "/prob/p194781",
    "/prob/p163932",
    "/prob/p101409",
    "/prob/p192383",
    "/prob/p158888",
    "/prob/p170371",
    "/prob/p184029",
    "/prob/p101372",
    "/prob/p170924",
    "/prob/p118230",
    "/prob/p108997",
    "/prob/p135988",
    "/prob/p173469",
    "/prob/p183394",
    "/prob/p158175",
    "/prob/p105722",
    "/prob/p154048",
    "/prob/p161124",
    "/prob/p167015",
    "/prob/p104029",
    "/prob/p143900",
    "/prob/p137918",
    "/prob/p183174",
    "/prob/p186177",
    "/prob/p118182",
    "/prob/p195413"
  ],
  "http://codingbat.com/java/Recursion-2": [
    "/prob/p145416",
    "/prob/p199368",
    "/prob/p169605",
    "/prob/p138907",
    "/prob/p105136",
    "/prob/p185204",
    "/prob/p171660",
    "/prob/p168295"
  ],
  "http://codingbat.com/java/Map-1": [
    "/prob/p197888",
    "/prob/p148813",
    "/prob/p107259",
    "/prob/p182712",
    "/prob/p196458",
    "/prob/p128461",
    "/prob/p115011",
    "/prob/p115012",
    "/prob/p136950"
  ],
  "http://codingbat.com/java/Map-2": [
    "/prob/p152303",
    "/prob/p125327",
    "/prob/p126332",
    "/prob/p117630",
    "/prob/p168493",
    "/prob/p103593",
    "/prob/p190862",
    "/prob/p134133",
    "/prob/p150113"
  ],
  "http://codingbat.com/java/Functional-1": [
    "/prob/p117665",
    "/prob/p139586",
    "/prob/p170181",
    "/prob/p181634",
    "/prob/p177528",
    "/prob/p103869",
    "/prob/p152194",
    "/prob/p186894",
    "/prob/p105967"
  ],
  "http://codingbat.com/java/Functional-2": [
    "/prob/p103456",
    "/prob/p124510",
    "/prob/p137274",
    "/prob/p105671",
    "/prob/p194496",
    "/prob/p184496",
    "/prob/p115967",
    "/prob/p148198",
    "/prob/p132748"
  ]
}